consul/__init__.py
consul/aio.py
consul/base.py
consul/std.py
consul/tornado.py
consul/twisted.py
consul_reborn-1.4.0.dist-info/LICENSE
consul_reborn-1.4.0.dist-info/METADATA
consul_reborn-1.4.0.dist-info/WHEEL
consul_reborn-1.4.0.dist-info/top_level.txt
consul_reborn-1.4.0.dist-info/RECORD
