Metadata-Version: 2.1
Name: consul-reborn
Version: 1.4.0
Summary: Fork of Python client for Consul (http://www.consul.io/) with some community and my patches.
Home-page: https://github.com/nixargh/python-consul
Author: nixargh
Author-email: nixargh@protonmail.com
License: MIT
Platform: UNKNOWN
Classifier: Development Status :: 5 - Production/Stable
Classifier: License :: OSI Approved :: MIT License
Classifier: Programming Language :: Python :: 3
Classifier: Topic :: System :: Systems Administration
Requires-Dist: requests (>=2.0)
Requires-Dist: requests-unixsocket (>=0.1.5)
Requires-Dist: six (>=1.4)
Provides-Extra: asyncio
Requires-Dist: aiohttp ; extra == 'asyncio'
Provides-Extra: tornado
Requires-Dist: tornado ; extra == 'tornado'
Provides-Extra: twisted
Requires-Dist: twisted ; extra == 'twisted'
Requires-Dist: treq ; extra == 'twisted'
